{
"stripWhitespaceX": false,
"stripWhitespaceY": false,
"rotation": false,
"alias": true,
"ignoreBlankImages": false,
"alphaThreshold": 0,
"minWidth": 16,
"minHeight": 16,
"maxWidth": 4096,
"maxHeight": 4096,
"pot": true,
"multipleOfFour": false,
"square": true,
"outputFormat": "png",
"jpegQuality": 0.9,
"premultiplyAlpha": false,
"bleed": true,
"scale": [ 1 ],
"scaleSuffix": [ "" ],
"scaleResampling": [ "bicubic" ],
"paddingX": 2,
"paddingY": 2,
"edgePadding": true,
"duplicatePadding": true,
"filterMin": "Linear",
"filterMag": "Linear",
"wrapX": "ClampToEdge",
"wrapY": "ClampToEdge",
"format": "RGBA8888",
"atlasExtension": ".atlas",
"combineSubdirectories": false,
"flattenPaths": false,
"useIndexes": false,
"debug": false,
"fast": false,
"limitMemory": true,
"currentProject": true,
"packing": "rectangles",
"silent": false,
"ignore": false,
"bleedIterations": 2
}